Metadata-Version: 2.1
Name: video-summarizer
Version: 0.0.1
Summary: A time saver tool that transform long footage in a short video keeping the meaningful parts. Useful to compress video surveillance footage.
Home-page: https://github.com/lanzani/video_summarizer
Author: Federico Lanzani
Author-email: federico.finder@gmail.com
License: MIT
Download-URL: https://github.com/lanzani/video_summarizer/archive/refs/tags/v0.0.1.tar.gz
Keywords: video analysis,video summarization,surveillance
Platform: UNKNOWN
Classifier: Development Status :: 3 - Alpha
Classifier: Intended Audience :: Developers
Classifier: Topic :: Software Development :: Build Tools
Classifier: License :: OSI Approved :: MIT License
Classifier: Programming Language :: Python :: 3
Classifier: Programming Language :: Python :: 3.7
Classifier: Programming Language :: Python :: 3.8
Classifier: Programming Language :: Python :: 3.9
